README.md
setup.py
cmdbtools/__init__.py
cmdbtools/cmdbtools.py
cmdbtools.egg-info/PKG-INFO
cmdbtools.egg-info/SOURCES.txt
cmdbtools.egg-info/dependency_links.txt
cmdbtools.egg-info/entry_points.txt
cmdbtools.egg-info/requires.txt
cmdbtools.egg-info/top_level.txt