Metadata-Version: 2.1
Name: cmdbtools
Version: 1.1.3
Summary: cmdbtools: A command line tools for CMDB variant browser.
Home-page: https://github.com/ShujiaHuang/cmdbtools
Author: Shujia Huang
Author-email: huangshujia9@gmail.com
Maintainer: Shujia Huang
Maintainer-email: huangshujia9@gmail.com
License: BSD (3-clause)
Download-URL: https://github.com/ShujiaHuang/cmdbtools
Platform: UNKNOWN
Classifier: Intended Audience :: Science/Research
Classifier: Programming Language :: Python :: 3.7
Classifier: Programming Language :: Python :: 3.8
Classifier: Programming Language :: Python :: 3.9
Classifier: License :: OSI Approved :: BSD License
Classifier: Topic :: Scientific/Engineering :: Bio-Informatics
Classifier: Operating System :: POSIX
Classifier: Operating System :: POSIX :: Linux
Classifier: Operating System :: MacOS
